sci_dl/__init__.py
sci_dl/main.py
sci_dl/sci_dl.py
sci_dl/locale/zh_CN/LC_MESSAGES/sci-dl.mo
sci_dl-0.1.2.dist-info/METADATA
sci_dl-0.1.2.dist-info/WHEEL
sci_dl-0.1.2.dist-info/entry_points.txt
sci_dl-0.1.2.dist-info/top_level.txt
sci_dl-0.1.2.dist-info/RECORD
