Metadata-Version: 2.1
Name: sci-dl
Version: 0.1.2
Summary: sci-dl: help you download SciHub PDF programmatically
Home-page: https://github.com/soultoolman/sci-dl
Author: soultoolman
Author-email: soultooman@gmail.com
License: MIT
Platform: UNKNOWN
Classifier: License :: OSI Approved :: MIT License
Classifier: Programming Language :: Python
Classifier: Programming Language :: Python :: 3
Classifier: Programming Language :: Python :: 3.6
Classifier: Programming Language :: Python :: Implementation :: CPython
Classifier: Programming Language :: Python :: Implementation :: PyPy
Classifier: Topic :: Scientific/Engineering :: Bio-Informatics
Requires-Python: >=3.6.0
Requires-Dist: requests
Requires-Dist: beautifulsoup4
Provides-Extra: cmd
Requires-Dist: appdirs ; extra == 'cmd'
Requires-Dist: click ; extra == 'cmd'
Requires-Dist: validators ; extra == 'cmd'
Requires-Dist: rich ; extra == 'cmd'
Requires-Dist: pysocks ; extra == 'cmd'
